{"trial_id": "03", "hyperparameters": {"space": [{"class_name": "Int", "config": {"name": "input_units", "default": null, "conditions": [], "min_value": 16, "max_value": 128, "step": 16, "sampling": "linear"}}, {"class_name": "Float", "config": {"name": "dropout_1", "default": 0.1, "conditions": [], "min_value": 0.1, "max_value": 0.5, "step": 0.1, "sampling": "linear"}}, {"class_name": "Int", "config": {"name": "n_layers", "default": null, "conditions": [], "min_value": 1, "max_value": 3, "step": 1, "sampling": "linear"}}, {"class_name": "Int", "config": {"name": "hidden_units_0", "default": null, "conditions": [], "min_value": 8, "max_value": 64, "step": 8, "sampling": "linear"}}, {"class_name": "Float", "config": {"name": "dropout_2", "default": 0.1, "conditions": [], "min_value": 0.1, "max_value": 0.5, "step": 0.1, "sampling": "linear"}}, {"class_name": "Choice", "config": {"name": "learning_rate", "default": 0.01, "conditions": [], "values": [0.01, 0.001, 0.0001], "ordered": true}}, {"class_name": "Int", "config": {"name": "hidden_units_1", "default": null, "conditions": [], "min_value": 8, "max_value": 64, "step": 8, "sampling": "linear"}}, {"class_name": "Float", "config": {"name": "dropout_3", "default": 0.1, "conditions": [], "min_value": 0.1, "max_value": 0.5, "step": 0.1, "sampling": "linear"}}, {"class_name": "Int", "config": {"name": "hidden_units_2", "default": null, "conditions": [], "min_value": 8, "max_value": 64, "step": 8, "sampling": "linear"}}, {"class_name": "Float", "config": {"name": "dropout_4", "default": 0.1, "conditions": [], "min_value": 0.1, "max_value": 0.5, "step": 0.1, "sampling": "linear"}}], "values": {"input_units": 128, "dropout_1": 0.1, "n_layers": 1, "hidden_units_0": 48, "dropout_2": 0.1, "learning_rate": 0.0001, "hidden_units_1": 64, "dropout_3": 0.1, "hidden_units_2": 24, "dropout_4": 0.30000000000000004}}, "metrics": {"metrics": {"accuracy": {"direction": "max", "observations": [{"value": [0.9697802066802979], "step": 44}]}, "loss": {"direction": "min", "observations": [{"value": [0.10279887914657593], "step": 44}]}, "precision": {"direction": "max", "observations": [{"value": [0.9742489457130432], "step": 44}]}, "recall": {"direction": "max", "observations": [{"value": [0.9784482717514038], "step": 44}]}, "val_accuracy": {"direction": "max", "observations": [{"value": [0.9780219793319702], "step": 44}]}, "val_loss": {"direction": "min", "observations": [{"value": [0.07442858815193176], "step": 44}]}, "val_precision": {"direction": "max", "observations": [{"value": [0.9811320900917053], "step": 44}]}, "val_recall": {"direction": "max", "observations": [{"value": [0.9811320900917053], "step": 44}]}}}, "score": 0.9780219793319702, "best_step": 44, "status": "COMPLETED", "message": null}